{
  "combo_key": "EqualizationTransform -> ColorSpaceTransform -> NormalizeTransform",
  "confidence_level": "high_con",
  "transforms": [
    "EqualizationTransform",
    "ColorSpaceTransform",
    "NormalizeTransform"
  ],
  "accuracy": 0.9751449875724938,
  "alpha": 0.0041425020712509975,
  "gamma": 1.069944899216261,
  "weighted_alpha": 0.003871696639972205,
  "confusion_matrix": {
    "TP": 599,
    "TN": 578,
    "FP": 20,
    "FN": 10
  },
  "training_time_seconds": 12.317660093307495,
  "gradcam_images": [
    {
      "image_id": "img_00508",
      "label": 0,
      "confidence": 1.7881393432617188e-07,
      "pos_overlay": "gradcam_pos_img_00508.png",
      "neg_overlay": "gradcam_neg_img_00508.png"
    },
    {
      "image_id": "img_00548",
      "label": 0,
      "confidence": 0.423828125,
      "pos_overlay": "gradcam_pos_img_00548.png",
      "neg_overlay": "gradcam_neg_img_00548.png"
    },
    {
      "image_id": "img_00045",
      "label": 0,
      "confidence": 0.591796875,
      "pos_overlay": "gradcam_pos_img_00045.png",
      "neg_overlay": "gradcam_neg_img_00045.png"
    },
    {
      "image_id": "img_00019",
      "label": 1,
      "confidence": 1.0,
      "pos_overlay": "gradcam_pos_img_00019.png",
      "neg_overlay": "gradcam_neg_img_00019.png"
    },
    {
      "image_id": "img_00013",
      "label": 1,
      "confidence": 0.50048828125,
      "pos_overlay": "gradcam_pos_img_00013.png",
      "neg_overlay": "gradcam_neg_img_00013.png"
    },
    {
      "image_id": "img_00081",
      "label": 1,
      "confidence": 0.044586181640625,
      "pos_overlay": "gradcam_pos_img_00081.png",
      "neg_overlay": "gradcam_neg_img_00081.png"
    }
  ]
}