{
  "combo_key": "NormalizeTransform -> ColorSpaceTransform -> EqualizationTransform",
  "confidence_level": "base",
  "transforms": [
    "NormalizeTransform",
    "ColorSpaceTransform",
    "EqualizationTransform"
  ],
  "accuracy": 0.9469759734879868,
  "alpha": -0.024026512013256007,
  "gamma": 0.8659403757343556,
  "weighted_alpha": -0.027746150527835668,
  "confusion_matrix": {
    "TP": 562,
    "TN": 581,
    "FP": 17,
    "FN": 47
  },
  "training_time_seconds": 12.440839529037476,
  "gradcam_images": [
    {
      "image_id": "img_00933",
      "label": 0,
      "confidence": 7.748603820800781e-07,
      "pos_overlay": "gradcam_pos_img_00933.png",
      "neg_overlay": "gradcam_neg_img_00933.png"
    },
    {
      "image_id": "img_00162",
      "label": 0,
      "confidence": 0.485595703125,
      "pos_overlay": "gradcam_pos_img_00162.png",
      "neg_overlay": "gradcam_neg_img_00162.png"
    },
    {
      "image_id": "img_00082",
      "label": 0,
      "confidence": 0.5400390625,
      "pos_overlay": "gradcam_pos_img_00082.png",
      "neg_overlay": "gradcam_neg_img_00082.png"
    },
    {
      "image_id": "img_00007",
      "label": 1,
      "confidence": 1.0,
      "pos_overlay": "gradcam_pos_img_00007.png",
      "neg_overlay": "gradcam_neg_img_00007.png"
    },
    {
      "image_id": "img_01009",
      "label": 1,
      "confidence": 0.51513671875,
      "pos_overlay": "gradcam_pos_img_01009.png",
      "neg_overlay": "gradcam_neg_img_01009.png"
    },
    {
      "image_id": "img_00015",
      "label": 1,
      "confidence": 0.451416015625,
      "pos_overlay": "gradcam_pos_img_00015.png",
      "neg_overlay": "gradcam_neg_img_00015.png"
    }
  ]
}